[
    {
        "path": "d:\\DOANupdate4-master\\uploads\\49f41046-ac17-4826-9157-b470d4e0f3f8_test.docx",
        "form_data": {
            "document_name": "đat",
            "Địa chỉ ở đâu:": "h",
            "Tên tôi là:": "h",
            "Địa chỉ:": "h",
            "Mày là ai:": "h",
            "Sđt:": "h",
            "Email của bạn:": "h",
            "Cứ nhân ngành": "h",
            "Đại học": "h",
            "Sau khi tốt nghiệp, tôi làm việc ở vị trí": "h",
            "Công ty": "h",
            "Với": "h",
            "ngày": "h",
            "tháng": "h",
            "năm": "h",
            "Họ tên": "h"
        },
        "timestamp": "2025-03-31T11:56:35.029290",
        "user_id": 1,
        "user_name": "Nguyễn Tuấn Đạt"
    },
    {
        "form_id": "8bc3143b-68b6-484f-80d1-e6f671974135",
        "path": "d:\\updatelan5-master\\uploads\\eccf393b-9f01-4daa-ac08-aea2d65d20b4_test.docx",
        "form_data": {
            "form_id": "8bc3143b-68b6-484f-80d1-e6f671974135",
            "document_name": "dat",
            "Địa chỉ ở đâu:": "2",
            "Tên tôi là:": "1",
            "Địa chỉ:": "1",
            "Mày là ai:": "1",
            "Sđt:": "1",
            "Email của bạn:": "1",
            "Cứ nhân ngành": "1",
            "Đại học": "1",
            "Sau khi tốt nghiệp, tôi làm việc ở vị trí": "1",
            "Công ty": "1",
            "Với": "1",
            "ngày": "1",
            "tháng": "1",
            "năm": "1",
            "Họ tên": "1"
        },
        "timestamp": "2025-03-31T16:36:01.045452",
        "user_id": 2,
        "user_name": "đạt"
    },
    {
        "form_id": "27e855b1-1cff-403a-9433-4f74c921ae27",
        "path": "d:\\updatelan5-master\\uploads\\622081cb-f8d2-4e2c-b179-64d7a39fa68b_test.docx",
        "form_data": {
            "form_id": "27e855b1-1cff-403a-9433-4f74c921ae27",
            "document_name": "",
            "Địa chỉ ở đâu:": "2",
            "Tên tôi là:": "2",
            "Địa chỉ:": "2",
            "Mày là ai:": "2",
            "Sđt:": "2",
            "Email của bạn:": "2",
            "Cứ nhân ngành": "2",
            "Đại học": "2",
            "Sau khi tốt nghiệp, tôi làm việc ở vị trí": "2",
            "Công ty": "2",
            "Với": "2",
            "ngày": "2",
            "tháng": "2",
            "năm": "2",
            "Họ tên": "2"
        },
        "timestamp": "2025-03-31T17:43:50.360082",
        "user_id": 1,
        "user_name": "Nguyễn Tuấn Đạt"
    },
    {
        "form_id": "76c9e1bd-7043-4b48-a93a-bfbf733bdf0b",
        "path": "/app/uploads/b7e61ca1-f2f8-41e1-ba14-a3c06ad0abd5_test.docx",
        "form_data": {
            "form_id": "76c9e1bd-7043-4b48-a93a-bfbf733bdf0b",
            "document_name": "dat",
            "Địa chỉ ở đâu:": "2",
            "Tên tôi là:": "21",
            "Địa chỉ:": "1",
            "Mày là ai:": "1",
            "Sđt:": "1",
            "Email của bạn:": "1",
            "Cứ nhân ngành": "1",
            "Đại học": "1",
            "Sau khi tốt nghiệp, tôi làm việc ở vị trí": "1",
            "Công ty": "1",
            "Với": "1",
            "ngày": "1",
            "tháng": "1",
            "năm": "1",
            "Họ tên": "1"
        },
        "timestamp": "2025-04-01T07:07:47.869168",
        "user_id": 1,
        "user_name": "Nguyễn Tuấn Đạt"
    }
]